ukcompanies/__init__.py
ukcompanies/__main__.py
ukcompanies/auth.py
ukcompanies/client.py
ukcompanies/client_endpoints.py
ukcompanies/config.py
ukcompanies/exceptions.py
ukcompanies/retry.py
ukcompanies/cli/__init__.py
ukcompanies/cli/main.py
ukcompanies/models/__init__.py
ukcompanies/models/address.py
ukcompanies/models/appointment.py
ukcompanies/models/base.py
ukcompanies/models/company.py
ukcompanies/models/disqualification.py
ukcompanies/models/document.py
ukcompanies/models/filing.py
ukcompanies/models/officer.py
ukcompanies/models/rate_limit.py
ukcompanies/models/search.py
ukcompanies/services/__init__.py
ukcompanies-0.6.1.dist-info/METADATA
ukcompanies-0.6.1.dist-info/WHEEL
ukcompanies-0.6.1.dist-info/entry_points.txt
ukcompanies-0.6.1.dist-info/licenses/LICENSE
ukcompanies-0.6.1.dist-info/RECORD
