Metadata-Version: 2.4
Name: ukcompanies
Version: 0.6.1
Summary: A Python SDK for accessing UK Companies House API
Project-URL: homepage, https://github.com/dkellett/ukcompanies
Project-URL: repository, https://github.com/dkellett/ukcompanies
Project-URL: documentation, https://github.com/dkellett/ukcompanies/tree/main/docs
Author-email: Development Team <dev@example.com>
License: MIT
License-File: LICENSE
Keywords: api,business,companies,data,house,sdk,uk
Classifier: Development Status :: 4 - Beta
Classifier: Intended Audience :: Developers
Classifier: License :: OSI Approved :: MIT License
Classifier: Programming Language :: Python :: 3
Classifier: Programming Language :: Python :: 3.10
Classifier: Programming Language :: Python :: 3.11
Classifier: Programming Language :: Python :: 3.12
Classifier: Topic :: Office/Business
Classifier: Topic :: Software Development :: Libraries :: Python Modules
Requires-Python: >=3.10
Requires-Dist: click>=8.1.7
Requires-Dist: httpx>=0.27.0
Requires-Dist: pydantic>=2.9.0
Requires-Dist: python-dateutil>=2.9.0
Requires-Dist: python-dotenv>=1.0.1
Requires-Dist: structlog>=24.4.0
Requires-Dist: twine>=6.1.0
Provides-Extra: dev
Requires-Dist: mypy>=1.11.0; extra == 'dev'
Requires-Dist: pytest-asyncio>=0.24.0; extra == 'dev'
Requires-Dist: pytest>=8.3.0; extra == 'dev'
Requires-Dist: respx>=0.21.0; extra == 'dev'
Requires-Dist: ruff>=0.7.0; extra == 'dev'
Provides-Extra: docs
Requires-Dist: mkdocs-material>=9.5.0; extra == 'docs'
Requires-Dist: mkdocs>=1.6.0; extra == 'docs'
